parq/__init__.py
parq/main.py
parquet_cli-1.3.dist-info/LICENSE
parquet_cli-1.3.dist-info/METADATA
parquet_cli-1.3.dist-info/WHEEL
parquet_cli-1.3.dist-info/entry_points.txt
parquet_cli-1.3.dist-info/top_level.txt
parquet_cli-1.3.dist-info/RECORD
