Metadata-Version: 2.1
Name: parquet-cli
Version: 1.3
Summary: Command line (CLI) tool to inspect Apache Parquet files on the go
Home-page: https://github.com/chhantyal/parquet-cli
Author: Nar Kumar Chhantyal
Author-email: nkchhantyal@gmail.com
License: BSD 3-Clause License
Platform: any
Classifier: Development Status :: 3 - Alpha
Classifier: Intended Audience :: Developers
Classifier: Programming Language :: Python
Classifier: Programming Language :: Python :: 3
Classifier: Programming Language :: Python :: 2
Classifier: Programming Language :: Python :: Implementation :: CPython
Classifier: Programming Language :: Python :: Implementation :: PyPy
Requires-Dist: pandas (>=0.22.0)
Requires-Dist: pyarrow (>=0.9.0.post1)
